{
  "LEVEL13_ROOM1": "qj365109l3uhrc36nlr8q1ide8@group.calendar.google.com",
  "LEVEL13_ROOM2": "qj365109l3uhrc36nlr8q1ide8@group.calendar.google.com",
  "LEVEL13_ROOM3": "qj365109l3uhrc36nlr8q1ide8@group.calendar.google.com",
  "LEVEL13_ROOM4": "qj365109l3uhrc36nlr8q1ide8@group.calendar.google.com",
  "LEVEL13_ROOM5": "qj365109l3uhrc36nlr8q1ide8@group.calendar.google.com",
  "LEVEL13_VECE": "0prpnj29dl5gd2rbak8d2lc0ds@group.calendar.google.com",
  "LEVEL14_ROOM1": "qj365109l3uhrc36nlr8q1ide8@group.calendar.google.com",
  "LEVEL14_ROOM2": "qj365109l3uhrc36nlr8q1ide8@group.calendar.google.com",
  "LEVEL14_ROOM3": "qj365109l3uhrc36nlr8q1ide8@group.calendar.google.com",
  "LEVEL14_ROOM4": "qj365109l3uhrc36nlr8q1ide8@group.calendar.google.com",
  "LEVEL14_ROOM5": "qj365109l3uhrc36nlr8q1ide8@group.calendar.google.com"
}
